busylite/__init__.py
busylite/scripts/__init__.py
busylite/scripts/busycli.py
busylite-0.1.1.dist-info/LICENSE
busylite-0.1.1.dist-info/METADATA
busylite-0.1.1.dist-info/WHEEL
busylite-0.1.1.dist-info/entry_points.txt
busylite-0.1.1.dist-info/top_level.txt
busylite-0.1.1.dist-info/RECORD
