Metadata-Version: 2.1
Name: busylite
Version: 0.1.1
Summary: Package to interact with a Kuando Busylight
Home-page: https://gitlab.com/ryanmcginger/busylite
Author: Ryan McCarthy
Author-email: code@mcginger.net
License: MIT License
Keywords: busylight hid busylite
Platform: UNKNOWN
Classifier: Programming Language :: Python :: 3.8
Requires-Dist: click
Requires-Dist: numpy
Requires-Dist: hidapi
Requires-Dist: flask
Requires-Dist: flask-httpauth
